<?xml version="1.0" encoding="UTF-8"?>
<!DOCTYPE hibernate-mapping PUBLIC "-//Hibernate/Hibernate Mapping DTD 3.0//EN"
"http://hibernate.sourceforge.net/hibernate-mapping-3.0.dtd">
<!-- 
    Mapping file autogenerated by MyEclipse Persistence Tools
-->
<hibernate-mapping>
    <class name="com.quix.aia.cn.imo.data.addressbook.CandidateTrainingDetail" table="T_CANDIDATE_TRAINING_DETAIL" >
    <cache usage="read-write"/>
     
        <id name="detailCode" type="java.lang.Integer" >
            <column name="DETAIL_CODE"  />
            <generator class = "native"/>
      	</id>
      
        <property  name="courseCode" type="java.lang.String">
            <column name="COURSE_CODE"  />
        </property>
        
         <property  name="courseName" type="java.lang.String">
            <column name="COURSE_NAME"  />
        </property>
        
         <property  name="curriculamCode" type="java.lang.String">
            <column name="CURRICULAM_CODE"  />
        </property>
        
         <property  name="courseType" type="java.lang.String">
            <column name="COURSE_TYPE"  />
        </property>
        
        <property  name="startDate" type="java.util.Date">
            <column name="START_DATE"  />
        </property>
        
        <property  name="creationDate" type="java.util.Date">
            <column name="CREATION_DATE"  />
        </property>
       
    </class>
</hibernate-mapping>