<?xml version="1.0" encoding="UTF-8"?>
<!DOCTYPE hibernate-mapping PUBLIC "-//Hibernate/Hibernate Mapping DTD 3.0//EN"
"http://hibernate.sourceforge.net/hibernate-mapping-3.0.dtd">
<!-- 
    Mapping file autogenerated by MyEclipse Persistence Tools
-->
<hibernate-mapping>
    <class name="com.quix.aia.cn.imo.data.interview.Interview" table="T_INTERVIEW" >
     <cache usage="read-write"/>
     <id name="interview_code" type="java.lang.Integer" >
            <column name="INTERVIEW_CODE"  />
             <generator class = "native"/>
      </id>
        
        <property  name="interviewType" type="java.lang.String">
            <column name="INTERVIEW_TYPE"  />
        </property>
        
        <property  name="interviewSessionName" type="java.lang.String">
            <column name="INTERVIEW_SESSION_NAME"  />
        </property>
        
        <property  name="interviewDate" type="java.util.Date">
            <column name="INTERVIEW_DATE"  />
        </property>
        
        <property  name="StartTime" type="java.util.Date">
            <column name="START_TIME"  />
        </property>
        
        <property  name="EndTime" type="java.util.Date">
            <column name="END_TIME"  />
        </property>
        
        
         <property  name="location" type="java.lang.String">
            <column name="LOCATION"  />
        </property>
        
         <property  name="interviewMaterial" type="java.lang.String">
            <column name="INTERVIEW_MATERIAL"  />
        </property>
        
         <property  name="estimatedCondidates" type="java.lang.Integer">
            <column name="ESTIMATED_CANDIDATES"  />
        </property>
        

        <property  name="buCode" type="java.lang.Integer">
            <column name="BU"  />
        </property>
        
        <property  name="cityCode" type="java.lang.String">
            <column name="CITY"  />
        </property>
        
        <property  name="sscCode" type="java.lang.String">
            <column name="SSC"  />
        </property>
        
         <property  name="branchCode" type="java.lang.Integer">
            <column name="BRANCH"  />
        </property>
        
          <property  name="token" type="java.lang.String">
            <column name="TOKETN"  />
        </property>
        
        <property  name="district" type="java.lang.Integer">
            <column name="DISTRICT"  />
        </property>
        
       
        <property  name="createdBy" type="java.lang.String">
            <column name="CREATED_BY"  />
        </property>
        
        <property  name="creationDate" type="java.util.Date">
            <column name="CREATION_DATE"  />
        </property>
        
        <property  name="modifiedBy" type="java.lang.String">
            <column name="MODIFIED_BY"  />
        </property>
        
        <property  name="modificationDate" type="java.util.Date">
            <column name="MODIFICATION_DATE"  />
        </property>
        
        <property  name="status" type="java.lang.Boolean">
            <column name="STATUS"  />
        </property>
        
        <property  name="officeCode" type="java.lang.String">
            <column name="OFFICE"  />
        </property>
        
        <property name="buName" formula="(SELECT b.BU_NAME FROM T_BU b where b.BU_CODE=BU)" update="false"></property>
        <property name="distName" formula="(SELECT d.DISTRICT_NAME FROM T_DISTRICT d WHERE d.DISTRICT_CODE=DISTRICT) " update="false"></property>
         <property name="branchName" formula="(SELECT b.BRANCH_FULLNAME FROM T_BRANCH b WHERE b.BRANCH_CODE=BRANCH) " update="false"></property>
         
          <property name="cityName" formula="(SELECT c.CITYNAME FROM CITY_ER c WHERE c.CITYCOD=CITY) " update="false"></property>
     <property name="sscName" formula="(SELECT s.LOCNAME FROM LOCAT_ER s WHERE s.LOCCODE=SSC AND s.CTYCOD=CITY ) " update="false"></property>
	<property name="officeName" formula="(SELECT b.OFFNAME FROM OFFICE_ER b WHERE b.OFFCOD=OFFICE and b.CTYCOD=CITY AND b.LOCCODE=SSC AND b.CO=(SELECT TB.BRANCH_NAME FROM T_BRANCH TB WHERE TB.BRANCH_CODE=BRANCH)) " update="false"></property>  
       <!--  <property name="organizer" formula="(SELECT u.STAFF_NAME FROM T_USER u WHERE u.USER_NO=CREATED_BY)" update="false"></property> -->
        
        
        <property name="registeredCount" formula="(SELECT COUNT(r.CANDIDATE_CODE) FROM T_INTERVIEW_REG r WHERE r.INTERVIEW_CODE=INTERVIEW_CODE AND r.STATUS = 1) " update="false"></property>
        <property name="attendeeCount" formula="(SELECT COUNT(r.CANDIDATE_CODE) FROM T_INTERVIEW_REG r WHERE r.INTERVIEW_CODE=INTERVIEW_CODE AND r.STATUS = 1 and r.INTERVIEW_RESULT!='') " update="false"></property>
        
        <property name="attachmentName" type="java.lang.String">
            <column name="TOPIC_FILE_NAME" length="300" />
        </property>
        <property name="attachmentPath" type="java.lang.String">
            <column name="TOPIC_FILE_PATH" length="300" />
        </property>  
       
    </class>
</hibernate-mapping>